{"权利—责任对等":{"权利—责任对等":{"currentFile":{"count":1,"lastUpdated":1767334673846}}},"搬家扔东西的时候":{"搬家扔东西的时候":{"currentFile":{"count":2,"lastUpdated":1767507214178}}},"仓位管理":{"仓位管理":{"internalLink":{"count":1,"lastUpdated":1768193044498}}},"持续参与能力":{"持续参与能力":{"currentFile":{"count":1,"lastUpdated":1768193425117}}},"dev-browser":{"dev-browser":{"currentFile":{"count":1,"lastUpdated":1768382752628}}},"skill":{"skill":{"currentFile":{"count":1,"lastUpdated":1768383030742}}},"agent-browser":{"agent-browser":{"currentFile":{"count":1,"lastUpdated":1768384029031}}},"react-best-practices":{"react-best-practices":{"currentFile":{"count":1,"lastUpdated":1769082791895}}}}